resampling/__init__.py
resampling-0.0.0.dist-info/METADATA
resampling-0.0.0.dist-info/RECORD
resampling-0.0.0.dist-info/WHEEL
resampling-0.0.0.dist-info/top_level.txt
