Metadata-Version: 2.1
Name: resampling
Version: 0.0.0
Summary: Resampling techniques and associated statistical inference
Home-page: https://github.com/artemmavrin/resampling
Author: Artem Mavrin
Author-email: amavrin@ucsd.edu
License: UNKNOWN
Platform: UNKNOWN
Classifier: Development Status :: 1 - Planning
Classifier: License :: OSI Approved :: MIT License
Classifier: Programming Language :: Python :: 3.7
